MANIFEST.in
setup.py
phreak/__init__.py
phreak/producthunt.py
phreak.egg-info/PKG-INFO
phreak.egg-info/SOURCES.txt
phreak.egg-info/dependency_links.txt
phreak.egg-info/entry_points.txt
phreak.egg-info/not-zip-safe
phreak.egg-info/requires.txt
phreak.egg-info/top_level.txt
phreak/data/__init__.py
phreak/data/phreak.png