Metadata-Version: 1.0
Name: phreak
Version: 0.0.3
Summary: Product Hunt app that sits in your System Tray
Home-page: http://captnemo.in/phreak
Author: Abhay Rana
Author-email: me@captnemo.in
License: MIT
Keywords: product hunt producthunt phreak tray
Platform: UNKNOWN
